{"MI/y5vTS/oaV3mVfdLhhYQ==":"mbr.jpg","RySyrkUrrPZPhzdrNWLxhg==":"mbr.jpeg","IedBUMFPy/wdQmKABiOf4g==":"mbr-1.jpg","X30aVRBEqsZY/bFEWmkiVg==":"mbr-2.jpg","YNiXBWgwNOjqA22Dmwqb5g==":"mbr-3.jpg","DrFPsfmeg5oSTFbYnhLeYw==":"mbr-4.jpg","6OY4DwgD2obALVw0F7NFIw==":"mbr-5.jpg","uEGJd4PrLTvFpgfDvYs4Lg==":"mbr-6.jpg","XRDdhODpZEaMtrsqfQDByg==":"mbr-7.jpg","+CFTCwDQuqe5qZvoVm36lQ==":"mbr-8.jpg","TDzMrNZ3G9e5ZOX+WKNHZA==":".png","uD7ommWiPsEzgjoXr7+7WA==":"-1.png","FevV3GW6F5q2kzdMs9kL9Q==":"img1.png","aXZEeqFSI5cDOPsN+RF3zQ==":"undraw-educator-re-ju47.png","XE0vtsu1lZsJ4dIqRM+feA==":"undraw-voice-control-ofo1.png","pvDzKP+U1ntyxq78TyTtHA==":"undraw-professor-re-mj1s.png","vJhiPDsAwXWmHENvVlkHTA==":"undraw-our-solution-re-8yk6.png","O8p9uTLtbu9wdUUK8EpLqQ==":"undraw-solution-mindset-re-57bf.png","3sovnyfUrcMeoFHJ4XUvZQ==":"undraw-thought-process-re-om58.png","PaOy8cvbIRx73A6aH0T9aQ==":"undraw-taking-notes-re-bnaf.png","uWxmlpCqgDSPBfof+uchww==":"undraw-design-feedback-re-8gtk.png","9HXLqjLJPPRPYnR2pyJlEw==":"undraw-redesign-feedback-re-jvm0.png","SmvMpWRa2jEAGn2wQTaOkA==":"header.png","KEXM56PaL/v0Gk98pgHyeg==":"header-1.png","EcrBkDrD6ZJCYwWXLkr2xg==":"header-2.png","7epA6Ps0Cv+CIjm1PBo6ew==":"img-2286.png","E7luX/+PwWThHcM8kegdqg==":"example.jpg","bUdLVFM6t/TZFX574sf54g==":"example.png","WcqF8e1oLT+1C7RDpNEOQQ==":"c2.png","AuwPAlg76tsvgCVkrGL5xQ==":"c1.png","wwhEH+yVrgZLXD52el6pGw==":"img-7362.jpg","239mi2yFGGKEvlgGB3HO8Q==":"wechatimg7093.png","eTcOYMqU96pqY7jC1cd/aQ==":"mbr.png","FtYvatGsgY4BLVI7823oPQ==":"jht.png","lqywMlGxgLlmkjrDYXRb1w==":"qs.png","oYMVu7mRlIGkWYrEV+mwcw==":"qs-1.png","8AZSdi8I3gQW7ZkeebekwQ==":"-2.png","njgj4yTOecUpq5HCGqJ7IQ==":"logo-1.png","U0J4dWQl6sM1bDpsiyXo2g==":"dm.png","kYYP5oVYsdC8LVENgRZ+Kg==":"jht-1.png","Wv2L72A+D0tqWDjobTORuA==":"nqgd.png","JFl7geni6m2s09q3xAE/0g==":"ym.png","cIZ+yqhJLHGhDrOKuqCtsA==":"ym-1.png","E+H0znhb2IE6U9BnWyI89g==":"ym-2.png","V+/+SAsB17rq+EjM6GsItw==":"-3.png","eubN0o2s728mwr68h4JvRA==":"-4.png","nueaq5XsPNW+14cQ3ZxGpg==":"-5.png","v+VIPiSVpPDvDSeAjArKvg==":"-6.png"}